{
  "_id": "IyfgazX7DaFaOiZv",
  "name": "Parchment",
  "type": "loot",
  "img": "icons/sundries/documents/document-symbol-circle-gold-red.webp",
  "data": {
    "description": {
      "value": "<p>A single sheet of heavier parchment paper.</p>",
      "chat": "",
      "unidentified": ""
    },
    "source": "PHB",
    "quantity": 1,
    "weight": 0,
    "price": "0.1",
    "attunement": 0,
    "equipped": false,
    "rarity": "common",
    "identified": true,
    "damage": {
      "parts": []
    }
  },
  "effects": [],
  "folder": null,
  "sort": 0,
  "permission": {
    "default": 0,
    "4lCdaYwhvK1T68Lv": 3
  },
  "flags": {
    "core": {
      "sourceId": "Compendium.dnd5e.items.WFQS2vT8ddrFjTJg"
    }
  }
}