{
  "name": "Red Dragon Scale Plate Armor",
  "type": "equipment",
  "img": "icons/equipment/chest/breastplate-banded-blue.webp",
  "data": {
    "description": {
      "value": "<p><span style=\"color:#191813;font-size:13px\">Plate consists of shaped, interlocking metal plates to cover the entire body. A suit of plate includes gauntlets, heavy leather boots, a visored helmet, and thick layers of padding underneath the armor. Buckles and straps distribute the weight over the body.</span></p>\n<p> </p>\n<p><span style=\"color:#191813\"><span style=\"font-size:13px\">Requires Attunement</span></span></p>\n<p> </p>\n<p><span style=\"color:#191813\"><span style=\"font-size:13px\">You have resistance to fire damage while you wear this armor.</span></span></p>",
      "chat": "",
      "unidentified": ""
    },
    "source": "",
    "quantity": 1,
    "weight": 65,
    "price": 0,
    "attunement": 1,
    "equipped": false,
    "rarity": "",
    "identified": true,
    "activation": {
      "type": "",
      "cost": 0,
      "condition": ""
    },
    "duration": {
      "value": null,
      "units": ""
    },
    "target": {
      "value": null,
      "width": null,
      "units": "",
      "type": ""
    },
    "range": {
      "value": null,
      "long": null,
      "units": ""
    },
    "uses": {
      "value": null,
      "max": "",
      "per": null
    },
    "consume": {
      "type": "",
      "target": null,
      "amount": null
    },
    "ability": null,
    "actionType": "",
    "attackBonus": 0,
    "chatFlavor": "",
    "critical": {
      "threshold": null,
      "damage": ""
    },
    "damage": {
      "parts": [],
      "versatile": ""
    },
    "formula": "",
    "save": {
      "ability": "",
      "dc": null,
      "scaling": "spell"
    },
    "armor": {
      "value": 18,
      "type": "heavy",
      "dex": null
    },
    "hp": {
      "value": 0,
      "max": 0,
      "dt": null,
      "conditions": ""
    },
    "baseItem": "plate",
    "speed": {
      "value": null,
      "conditions": ""
    },
    "strength": 0,
    "stealth": true,
    "proficient": true
  },
  "effects": [
    {
      "_id": "T95gQAjnLcfjwwFM",
      "changes": [
        {
          "key": "data.traits.dr.value",
          "mode": 2,
          "value": "fire",
          "priority": "20"
        }
      ],
      "disabled": false,
      "duration": {
        "startTime": null
      },
      "icon": "icons/svg/aura.svg",
      "label": "Red Dragon Armor",
      "origin": "Item.tWcUjUzjG14zY5cZ",
      "transfer": true,
      "flags": {
        "dae": {
          "stackable": "none",
          "specialDuration": [],
          "transfer": true
        }
      },
      "tint": null,
      "selectedKey": "data.traits.dr.value"
    }
  ],
  "folder": null,
  "sort": 0,
  "permission": {
    "default": 0,
    "QZauT3SEhPM1lH8w": 3
  },
  "flags": {
    "betterRolls5e": {
      "quickDesc": {
        "value": true,
        "altValue": true
      },
      "quickProperties": {
        "value": true,
        "altValue": true
      },
      "quickOther": {
        "value": true,
        "altValue": true
      },
      "quickFlavor": {
        "value": true,
        "altValue": true
      },
      "quickCharges": {
        "value": {
          "quantity": false
        },
        "altValue": {
          "quantity": false
        }
      }
    },
    "core": {
      "sourceId": "Item.tWcUjUzjG14zY5cZ"
    }
  },
  "_id": "8AnpWrrIUJZctM6F"
}