{
  "name": "Death Strike",
  "type": "feat",
  "img": "icons/magic/death/skull-poison-green.webp",
  "system": {
    "description": {
      "value": "<p>Starting at 17th level, you become a master of instant death. When you attack and hit a creature that is <strong>surprised</strong>, it must make a Constitution saving throw (DC 8 + your Dexterity modifier + your proficiency bonus). On a failed save, <strong>double</strong> the damage of your attack against the creature.</p>",
      "chat": "",
      "unidentified": ""
    },
    "source": "PHB",
    "activation": {
      "type": "special",
      "cost": 0,
      "condition": "When you attack and hit a creature that is surprised"
    },
    "duration": {
      "value": null,
      "units": "inst"
    },
    "target": {
      "value": 1,
      "width": null,
      "units": "",
      "type": "creature"
    },
    "range": {
      "value": null,
      "long": null,
      "units": ""
    },
    "uses": {
      "value": null,
      "max": "",
      "per": "",
      "recovery": ""
    },
    "consume": {
      "type": "",
      "target": "",
      "amount": null
    },
    "ability": "",
    "actionType": "save",
    "attackBonus": 0,
    "chatFlavor": "",
    "critical": {
      "threshold": null,
      "damage": ""
    },
    "damage": {
      "parts": [],
      "versatile": ""
    },
    "formula": "",
    "save": {
      "ability": "con",
      "dc": null,
      "scaling": "dex"
    },
    "requirements": "Assassin 17",
    "recharge": {
      "value": null,
      "charged": false
    }
  },
  "effects": [],
  "ownership": {
    "default": 0,
    "UjfixXuqstXNdypa": 3
  },
  "flags": {
    "magicitems": {
      "enabled": false,
      "equipped": false,
      "attuned": false,
      "charges": "0",
      "chargeType": "c1",
      "destroy": false,
      "destroyFlavorText": "reaches 0 charges: it crumbles into ashes and is destroyed.",
      "rechargeable": false,
      "recharge": "0",
      "rechargeType": "t1",
      "rechargeUnit": "r1",
      "sorting": "l"
    },
    "core": {
      "sourceId": "Item.qwzI7hr8DLhGHEY9"
    }
  },
  "_stats": {
    "systemId": "dnd5e",
    "systemVersion": "2.0.3",
    "coreVersion": "10.286",
    "createdTime": 1665206385723,
    "modifiedTime": 1665206568611,
    "lastModifiedBy": "UjfixXuqstXNdypa"
  },
  "folder": null,
  "sort": 0,
  "_id": "W8ypf607fON83Amv"
}