{
  "name": "Infusion: Returning Weapon",
  "type": "feat",
  "img": "icons/weapons/axes/axe-broad-brown.webp",
  "data": {
    "description": {
      "value": "<p><em>Item: A simple or martial weapon with the thrown property</em></p>\n<p>This magic weapon grants a +1 bonus to attack and damage rolls made with it, and it returns to the wielder’s hand immediately after it is used to make a ranged attack.</p>\n<section class=\"secret\">\n<p><em>Note: It's simplest to edit the chosen weapon directly and make note of it here for tracking purposes.</em></p>\n</section>",
      "chat": "",
      "unidentified": ""
    },
    "source": "TCE",
    "activation": {
      "type": "",
      "cost": 0,
      "condition": ""
    },
    "duration": {
      "value": null,
      "units": ""
    },
    "target": {
      "value": null,
      "width": null,
      "units": "",
      "type": ""
    },
    "range": {
      "value": null,
      "long": null,
      "units": ""
    },
    "uses": {
      "value": null,
      "max": "",
      "per": null
    },
    "consume": {
      "type": "",
      "target": null,
      "amount": null
    },
    "ability": null,
    "actionType": "",
    "attackBonus": 0,
    "chatFlavor": "",
    "critical": {
      "threshold": null,
      "damage": ""
    },
    "damage": {
      "parts": [],
      "versatile": ""
    },
    "formula": "",
    "save": {
      "ability": "",
      "dc": null,
      "scaling": "spell"
    },
    "requirements": "Artificer 2",
    "recharge": {
      "value": null,
      "charged": false
    }
  },
  "effects": [],
  "folder": null,
  "sort": 0,
  "permission": {
    "default": 0,
    "EHpONhziSoZpUpN3": 3
  },
  "flags": {
    "mre-dnd5e": {
      "formulaGroups": [
        {
          "label": "Primary",
          "formulaSet": []
        }
      ]
    },
    "magicitems": {
      "enabled": false,
      "equipped": false,
      "attuned": false,
      "charges": "0",
      "chargeType": "c1",
      "destroy": false,
      "destroyFlavorText": "reaches 0 charges: it crumbles into ashes and is destroyed.",
      "rechargeable": false,
      "recharge": "0",
      "rechargeType": "t1",
      "rechargeUnit": "r1",
      "sorting": "l"
    },
    "core": {
      "sourceId": "Item.GspRGcALTeqcVQRq"
    }
  },
  "_id": "RCOMGhM8p0GozX8W"
}