{
  "name": "Minor Conjuration",
  "type": "feat",
  "img": "icons/skills/melee/strike-weapons-orange.webp",
  "effects": [],
  "folder": null,
  "sort": 0,
  "flags": {
    "betterRolls5e": {
      "critRange": {
        "type": "String",
        "value": null
      },
      "critDamage": {
        "type": "String",
        "value": ""
      },
      "quickDesc": {
        "type": "Boolean",
        "value": true,
        "altValue": true
      },
      "quickAttack": {
        "type": "Boolean",
        "value": true,
        "altValue": true
      },
      "quickSave": {
        "type": "Boolean",
        "value": true,
        "altValue": true
      },
      "quickDamage": {
        "type": "Array",
        "value": [],
        "altValue": [],
        "context": []
      },
      "quickProperties": {
        "type": "Boolean",
        "value": true,
        "altValue": true
      },
      "quickCharges": {
        "type": "Boolean",
        "value": {
          "use": true,
          "resource": true,
          "charge": true
        },
        "altValue": {
          "use": true,
          "resource": true,
          "charge": true
        }
      },
      "quickTemplate": {
        "type": "Boolean",
        "value": true,
        "altValue": true
      },
      "quickOther": {
        "type": "Boolean",
        "value": true,
        "altValue": true,
        "context": ""
      },
      "quickFlavor": {
        "type": "Boolean",
        "value": true,
        "altValue": true
      },
      "quickPrompt": {
        "type": "Boolean",
        "value": false,
        "altValue": false
      }
    },
    "core": {
      "sourceId": "Item.YJuuM4bho5a7uYLO"
    },
    "magicitems": {
      "enabled": false,
      "equipped": false,
      "attuned": false,
      "charges": "0",
      "chargeType": "c1",
      "destroy": false,
      "destroyFlavorText": "reaches 0 charges: it crumbles into ashes and is destroyed.",
      "rechargeable": false,
      "recharge": "0",
      "rechargeType": "t1",
      "rechargeUnit": "r1",
      "sorting": "l"
    }
  },
  "_id": "aaguAzkotj1e3uap",
  "system": {
    "description": {
      "value": "<p>Starting at 2nd level when you select this school, you can use your action to conjure up an inanimate object in your hand or on the ground in an unoccupied space that you can see within 10 feet of you. This object can be no larger than 3 feet on a side and weigh no more than 10 pounds, and its form must be that of a nonmagical object that you have seen. The object is visibly magical, radiating dim light out to 5 feet.</p><p>The object disappears after 1 hour, when you use this feature again, or if it takes any damage.</p>",
      "chat": "",
      "unidentified": ""
    },
    "source": "PHB",
    "activation": {
      "type": "action",
      "cost": 1,
      "condition": ""
    },
    "duration": {
      "value": 1,
      "units": "hour"
    },
    "target": {
      "value": 1,
      "width": null,
      "units": "",
      "type": "object"
    },
    "range": {
      "value": 10,
      "long": null,
      "units": "ft"
    },
    "uses": {
      "value": 0,
      "max": "0",
      "per": "",
      "recovery": ""
    },
    "consume": {
      "type": "",
      "target": "",
      "amount": null
    },
    "ability": "",
    "actionType": "",
    "attackBonus": 0,
    "chatFlavor": "",
    "critical": {
      "threshold": null,
      "damage": null
    },
    "damage": {
      "parts": [],
      "versatile": ""
    },
    "formula": "",
    "save": {
      "ability": "",
      "dc": null,
      "scaling": "spell"
    },
    "requirements": "School of Conjuration 2",
    "recharge": {
      "value": null,
      "charged": false
    }
  },
  "ownership": {
    "default": 0,
    "LCw1mxC8S2Al3dWA": 3
  },
  "_stats": {
    "systemId": "dnd5e",
    "systemVersion": "2.0.3",
    "coreVersion": "10.286",
    "createdTime": null,
    "modifiedTime": 1665536033459,
    "lastModifiedBy": "UjfixXuqstXNdypa"
  }
}