{
  "_id": "2Vu5iLKk8RK0y2W6",
  "name": "Spirit Session",
  "type": "feat",
  "img": "icons/magic/symbols/star-inverted-yellow.webp",
  "data": {
    "description": {
      "value": "<p>By communing with spirits for an hour, you learn one Divination or Necromancy spell of your choice.</p>\n<details>\n<summary style=\"padding-bottom:8px\"><strong>Full Description</strong></summary>\n<blockquote style=\"font-style:normal\">\n<p>At 6th level, spirits provide you with supernatural insights. You can conduct an hour-long ritual channeling spirits (which can be done during a short or long rest) using your @Compendium[5e-complete.5e-class-features.qcpOFW8htwFxkMKC]{Spiritual Focus}. You can conduct the ritual with a number of <strong>willing creatures</strong> equal to your <strong>proficiency bonus</strong> (including yourself). At the end of the ritual, you temporarily learn one spell of your choice from any class.</p>\n<p>The spell you choose must be of a level equal to the number of creatures that conducted the ritual or less, the spell must of a level you can cast, and it must be in the school of <strong>Divination </strong>or <strong>Necromancy</strong>. The chosen spell counts as a bard spell for you but doesn’t count against the number of bard spells you know.</p>\n<p>Once you perform the ritual, you can’t do so again until you start a <strong>long rest</strong>, and you know the chosen spell until you start a long rest.</p>\n</blockquote>\n</details>",
      "chat": "",
      "unidentified": ""
    },
    "source": "VRGR",
    "activation": {
      "type": "hour",
      "cost": 1,
      "condition": ""
    },
    "duration": {
      "value": 1,
      "units": "day"
    },
    "target": {
      "value": null,
      "width": null,
      "units": "",
      "type": "self"
    },
    "range": {
      "value": null,
      "long": null,
      "units": ""
    },
    "uses": {
      "value": 1,
      "max": "1",
      "per": "lr"
    },
    "consume": {
      "type": "",
      "target": "",
      "amount": null
    },
    "ability": null,
    "actionType": "",
    "attackBonus": 0,
    "chatFlavor": "",
    "critical": {
      "threshold": null,
      "damage": ""
    },
    "damage": {
      "parts": [],
      "versatile": ""
    },
    "formula": "",
    "save": {
      "ability": "",
      "dc": null,
      "scaling": "spell"
    },
    "requirements": "College of Spirits 6",
    "recharge": {
      "value": null,
      "charged": false
    }
  },
  "effects": [],
  "folder": null,
  "sort": 0,
  "permission": {
    "default": 0,
    "LCw1mxC8S2Al3dWA": 3
  },
  "flags": {
    "betterRolls5e": {
      "quickDesc": {
        "value": true,
        "altValue": true
      },
      "quickProperties": {
        "value": true,
        "altValue": true
      },
      "quickOther": {
        "value": true,
        "altValue": true
      },
      "quickFlavor": {
        "value": true,
        "altValue": true
      },
      "quickCharges": {
        "value": {
          "use": true
        },
        "altValue": {
          "use": true
        }
      }
    },
    "core": {
      "sourceId": "Item.wVFAwdoZa6IeT7Lq"
    },
    "mre-dnd5e": {
      "formulaGroups": [
        {
          "label": "Primary",
          "formulaSet": []
        }
      ]
    },
    "magicitems": {
      "enabled": false,
      "equipped": false,
      "attuned": false,
      "charges": "0",
      "chargeType": "c1",
      "destroy": false,
      "destroyFlavorText": "reaches 0 charges: it crumbles into ashes and is destroyed.",
      "rechargeable": false,
      "recharge": "0",
      "rechargeType": "t1",
      "rechargeUnit": "r1",
      "sorting": "l"
    }
  }
}