{
  "_id": "0LdSLkrqY3h78lOo",
  "name": "Unsettling Words",
  "type": "feat",
  "img": "icons/magic/sonic/explosion-impact-shock-wave.webp",
  "data": {
    "description": {
      "value": "<p>Also at 3rd level, you can spin words laced with magic that unsettle a creature and cause it to doubt itself. As a bonus action, you can expend one use of your @Compendium[5e-complete.5e-class-features.7Q7X8BnKOsk2SXSt]{Bardic Inspiration} and choose one creature you can see within 60 feet of you. Roll the Bardic Inspiration die. The creature must <strong>subtract </strong>the number rolled from the next <strong>saving throw</strong> it makes before the start of your next turn.</p>\n<section class=\"secret\">\n<p><em>Note: When you add this feature to your character, set Resource Consumption to Item Uses: Bardic Inspiration.</em></p>\n</section>",
      "chat": "",
      "unidentified": ""
    },
    "source": "TCE",
    "activation": {
      "type": "bonus",
      "cost": 1,
      "condition": ""
    },
    "duration": {
      "value": 1,
      "units": "round"
    },
    "target": {
      "value": 1,
      "width": null,
      "units": "",
      "type": "creature"
    },
    "range": {
      "value": 60,
      "long": null,
      "units": "ft"
    },
    "uses": {
      "value": null,
      "max": "",
      "per": ""
    },
    "consume": {
      "type": "charges",
      "target": "",
      "amount": null
    },
    "ability": "",
    "actionType": "util",
    "attackBonus": 0,
    "chatFlavor": "",
    "critical": {
      "threshold": null,
      "damage": ""
    },
    "damage": {
      "parts": [
        [
          "@scale.bard.inspiration-die",
          ""
        ]
      ],
      "versatile": ""
    },
    "formula": "",
    "save": {
      "ability": "",
      "dc": null,
      "scaling": "spell"
    },
    "requirements": "College of Eloquence 3",
    "recharge": {
      "value": null,
      "charged": false
    }
  },
  "effects": [],
  "folder": null,
  "sort": 0,
  "permission": {
    "default": 0,
    "LCw1mxC8S2Al3dWA": 3
  },
  "flags": {
    "betterRolls5e": {
      "quickDesc": {
        "value": true,
        "altValue": true
      },
      "quickProperties": {
        "value": true,
        "altValue": true
      },
      "quickOther": {
        "value": true,
        "altValue": true,
        "context": ""
      },
      "quickFlavor": {
        "value": true,
        "altValue": true
      }
    },
    "core": {
      "sourceId": "Item.zsrpnPzniRgL5KeN"
    },
    "mre-dnd5e": {
      "formulaGroups": [
        {
          "label": "Inspiration Die",
          "formulaSet": [
            0
          ]
        }
      ]
    },
    "magicitems": {
      "enabled": false,
      "equipped": false,
      "attuned": false,
      "charges": "0",
      "chargeType": "c1",
      "destroy": false,
      "destroyFlavorText": "reaches 0 charges: it crumbles into ashes and is destroyed.",
      "rechargeable": false,
      "recharge": "0",
      "rechargeType": "t1",
      "rechargeUnit": "r1",
      "sorting": "l"
    }
  }
}