{
  "name": "Basilisk",
  "type": "npc",
  "img": "https://5etools-mirror-1.github.io/img/bestiary/MM/Basilisk.jpg",
  "data": {
    "abilities": {
      "str": {
        "value": 16,
        "proficient": 0,
        "bonuses": {
          "check": "",
          "save": 0
        },
        "mod": 3
      },
      "dex": {
        "value": 8,
        "proficient": 0,
        "bonuses": {
          "check": "",
          "save": 0
        },
        "mod": -1
      },
      "con": {
        "value": 15,
        "proficient": 0,
        "bonuses": {
          "check": "",
          "save": 0
        },
        "mod": 2
      },
      "int": {
        "value": 2,
        "proficient": 0,
        "bonuses": {
          "check": "",
          "save": 0
        },
        "mod": -4
      },
      "wis": {
        "value": 8,
        "proficient": 0,
        "bonuses": {
          "check": "",
          "save": 0
        },
        "mod": -1
      },
      "cha": {
        "value": 7,
        "proficient": 0,
        "bonuses": {
          "check": "",
          "save": 0
        },
        "mod": -2
      }
    },
    "attributes": {
      "ac": {
        "flat": 15,
        "calc": "natural",
        "formula": null,
        "min": 0,
        "value": null
      },
      "hp": {
        "value": 52,
        "min": 0,
        "max": 52,
        "temp": 0,
        "tempmax": 0,
        "formula": "8d8 + 16"
      },
      "init": {
        "value": 0,
        "bonus": 0,
        "mod": 0,
        "total": -1,
        "prof": 0
      },
      "movement": {
        "burrow": null,
        "climb": null,
        "fly": null,
        "swim": null,
        "walk": 20,
        "units": "ft",
        "hover": false
      },
      "attunement": {
        "max": 3
      },
      "senses": {
        "darkvision": 60,
        "blindsight": 0,
        "tremorsense": 0,
        "truesight": 0,
        "units": "ft",
        "special": ""
      },
      "spellcasting": "",
      "prof": 2,
      "spelldc": 8
    },
    "details": {
      "biography": {
        "value": "<div class=\"rd__b  rd__b--1\"><div class=\"rd__b  rd__b--2\"><p>Travelers sometimes find objects that look like pieces of remarkably lifelike stone carvings of wildlife. Missing parts appear to have been bitten off. Seasoned explorers regard such relics as warnings, knowing that the basilisk that created them is likely to be nearby.</p><div class=\"rd__b  rd__b--3\"><span class=\"rd__h rd__h--3\" data-title-index=\"2419\"> <span class=\"entry-title-inner\">Adaptable Predators.</span></span> <p>Basilisks thrive in arid, temperate, or tropical climates. They lair in caves or other sheltered sites. Most often, basilisks are encountered underground.</p><div class=\"rd__spc-inline-post\"></div><p>A basilisk born and raised in captivity can be domesticated and trained. Such a trained basilisk knows how to avoid meeting the eyes of those its master wishes to protect from its gaze, but it makes a daunting guardian beast. Because of this use, basilisk eggs are highly prized.</p></div><div class=\"rd__b  rd__b--3\"><span class=\"rd__h rd__h--3\" data-title-index=\"2420\"> <span class=\"entry-title-inner\">Gaze of Stone.</span></span> <p>Basilisks are ponderous for hunting creatures, but they needn't chase prey. Meeting a basilisk's supernatural gaze can be enough to affect a rapid transformation, transforming a victim into porous stone. Basilisks, with their strong jaws, are able to consume the stone. The stone returns to organic form in the basilisk's gullet.</p><div class=\"rd__spc-inline-post\"></div><p>Some alchemists are said to know how to process the basilisk's gullet and the fluids contained within. Properly handled, the gullet produces an oil that can return @condition[petrified] creatures to flesh and life. Unfortunately for such a victim, any parts lost in stone form remain absent if the creature revives. Revivification using the oil is impossible if a vital part of the @condition[petrified] creature, such as its head, is detached.</p></div></div></div>",
        "public": ""
      },
      "alignment": "unaligned",
      "race": "",
      "type": {
        "value": "monstrosity",
        "subtype": "",
        "swarm": null,
        "custom": ""
      },
      "environment": "Mountain",
      "cr": 3,
      "spellLevel": 0,
      "xp": {
        "value": 700
      },
      "source": "MM",
      "class": {}
    },
    "traits": {
      "size": "med",
      "di": {
        "value": [],
        "custom": ""
      },
      "dr": {
        "value": [],
        "custom": ""
      },
      "dv": {
        "value": [],
        "custom": ""
      },
      "ci": {
        "value": [],
        "custom": ""
      },
      "languages": {
        "value": [],
        "custom": ""
      }
    },
    "currency": {
      "pp": 0,
      "gp": 0,
      "ep": 0,
      "sp": 0,
      "cp": 0
    },
    "skills": {
      "acr": {
        "value": 0,
        "ability": "dex",
        "bonuses": {
          "check": 0,
          "passive": ""
        }
      },
      "ani": {
        "value": 0,
        "ability": "wis",
        "bonuses": {
          "check": 0,
          "passive": ""
        }
      },
      "arc": {
        "value": 0,
        "ability": "int",
        "bonuses": {
          "check": 0,
          "passive": ""
        }
      },
      "ath": {
        "value": 0,
        "ability": "str",
        "bonuses": {
          "check": 0,
          "passive": ""
        }
      },
      "dec": {
        "value": 0,
        "ability": "cha",
        "bonuses": {
          "check": 0,
          "passive": ""
        }
      },
      "his": {
        "value": 0,
        "ability": "int",
        "bonuses": {
          "check": 0,
          "passive": ""
        }
      },
      "ins": {
        "value": 0,
        "ability": "wis",
        "bonuses": {
          "check": 0,
          "passive": ""
        }
      },
      "itm": {
        "value": 0,
        "ability": "cha",
        "bonuses": {
          "check": 0,
          "passive": ""
        }
      },
      "inv": {
        "value": 0,
        "ability": "int",
        "bonuses": {
          "check": 0,
          "passive": ""
        }
      },
      "med": {
        "value": 0,
        "ability": "wis",
        "bonuses": {
          "check": 0,
          "passive": ""
        }
      },
      "nat": {
        "value": 0,
        "ability": "int",
        "bonuses": {
          "check": 0,
          "passive": ""
        }
      },
      "prc": {
        "value": 0,
        "ability": "wis",
        "bonuses": {
          "check": 0,
          "passive": ""
        }
      },
      "prf": {
        "value": 0,
        "ability": "cha",
        "bonuses": {
          "check": 0,
          "passive": ""
        }
      },
      "per": {
        "value": 0,
        "ability": "cha",
        "bonuses": {
          "check": 0,
          "passive": ""
        }
      },
      "rel": {
        "value": 0,
        "ability": "int",
        "bonuses": {
          "check": 0,
          "passive": ""
        }
      },
      "slt": {
        "value": 0,
        "ability": "dex",
        "bonuses": {
          "check": 0,
          "passive": ""
        }
      },
      "ste": {
        "value": 0,
        "ability": "dex",
        "bonuses": {
          "check": 0,
          "passive": ""
        }
      },
      "sur": {
        "value": 0,
        "ability": "wis",
        "bonuses": {
          "check": 0,
          "passive": ""
        }
      }
    },
    "spells": {
      "spell1": {
        "value": 0,
        "override": null,
        "max": 0
      },
      "spell2": {
        "value": 0,
        "override": null,
        "max": 0
      },
      "spell3": {
        "value": 0,
        "override": null,
        "max": 0
      },
      "spell4": {
        "value": 0,
        "override": null,
        "max": 0
      },
      "spell5": {
        "value": 0,
        "override": null,
        "max": 0
      },
      "spell6": {
        "value": 0,
        "override": null,
        "max": 0
      },
      "spell7": {
        "value": 0,
        "override": null,
        "max": 0
      },
      "spell8": {
        "value": 0,
        "override": null,
        "max": 0
      },
      "spell9": {
        "value": 0,
        "override": null,
        "max": 0
      },
      "pact": {
        "value": 0,
        "override": null
      },
      "spell0": {
        "value": 0,
        "max": 0
      }
    },
    "bonuses": {
      "mwak": {
        "attack": "",
        "damage": ""
      },
      "rwak": {
        "attack": "",
        "damage": ""
      },
      "msak": {
        "attack": "",
        "damage": ""
      },
      "rsak": {
        "attack": "",
        "damage": ""
      },
      "abilities": {
        "check": "",
        "save": "",
        "skill": ""
      },
      "spell": {
        "dc": ""
      }
    },
    "resources": {
      "legact": {
        "value": 0,
        "max": 0
      },
      "legres": {
        "value": 0,
        "max": 0
      },
      "lair": {
        "value": false,
        "initiative": 20
      }
    }
  },
  "token": {
    "vision": true,
    "disposition": -1,
    "displayBars": 40,
    "flags": {
      "monks-little-details": {
        "bloodsplat-colour": "#ff1000"
      },
      "monks-enhanced-journal": {
        "chatbubble": ""
      },
      "perfect-vision": {
        "visionRules": "default",
        "monoVisionColor": "",
        "sightLimit": null,
        "light": {}
      },
      "core": {
        "priority": null
      }
    },
    "displayName": 20,
    "bar1": {
      "attribute": "attributes.hp"
    },
    "bar2": {
      "attribute": null
    },
    "dimSight": 60,
    "brightSight": 0,
    "name": "Basilisk",
    "img": "https://assets.forge-vtt.com/6294414eee44137435f45555/assets/srd5e/img/MM/Basilisk.png",
    "width": 1,
    "height": 1,
    "scale": 1,
    "elevation": 0,
    "rotation": 0,
    "actorLink": false,
    "actorData": {},
    "effects": [],
    "randomImg": false,
    "mirrorX": false,
    "mirrorY": false,
    "lockRotation": false,
    "alpha": 1,
    "sightAngle": 0,
    "light": {
      "alpha": 0.5,
      "angle": 0,
      "bright": 0,
      "coloration": 1,
      "dim": 0,
      "gradual": true,
      "luminosity": 0.5,
      "saturation": 0,
      "contrast": 0,
      "shadows": 0,
      "animation": {
        "speed": 5,
        "intensity": 5,
        "reverse": false
      },
      "darkness": {
        "min": 0,
        "max": 1
      }
    }
  },
  "items": [
    {
      "data": {
        "description": {
          "value": "<div  class=\"rd__b  rd__b--3\"><p><i>Melee Weapon Attack:</i> [[/r 1d20+5]] (+5) to hit, reach 5 ft., one target. <i>Hit:</i> 10 ([[/r 2d6 + 3]]) piercing damage plus 7 ([[/r 2d6]]) poison damage.</p><div class=\"rd__spc-inline-post\"></div></div>",
          "chat": "",
          "unidentified": ""
        },
        "source": "MM",
        "quantity": 1,
        "weight": 0,
        "price": 0,
        "attunement": 0,
        "equipped": false,
        "rarity": "",
        "identified": true,
        "activation": {
          "type": "action",
          "cost": 1,
          "condition": ""
        },
        "duration": {
          "value": null,
          "units": ""
        },
        "target": {
          "value": null,
          "width": null,
          "units": "",
          "type": ""
        },
        "range": {
          "value": 5,
          "long": null,
          "units": "ft"
        },
        "uses": {
          "value": null,
          "max": "",
          "per": null
        },
        "consume": {
          "type": "",
          "target": null,
          "amount": null
        },
        "ability": "str",
        "actionType": "mwak",
        "attackBonus": 0,
        "chatFlavor": "",
        "critical": {
          "threshold": null,
          "damage": ""
        },
        "damage": {
          "parts": [
            [
              "2d6  + @mod",
              "piercing"
            ],
            [
              "2d6",
              "poison"
            ]
          ],
          "versatile": ""
        },
        "formula": "",
        "save": {
          "ability": "",
          "dc": null,
          "scaling": "spell"
        },
        "armor": {
          "value": 10
        },
        "hp": {
          "value": 0,
          "max": 0,
          "dt": null,
          "conditions": ""
        },
        "weaponType": "natural",
        "baseItem": "",
        "properties": {},
        "proficient": true,
        "recharge": {
          "value": null,
          "charged": false
        }
      },
      "name": "Bite",
      "type": "weapon",
      "img": "https://assets.forge-vtt.com/bazaar/core/icons/creatures/abilities/mouth-teeth-long-red.webp",
      "flags": {
        "srd5e": {
          "page": "monsterAction",
          "source": "MM",
          "hash": "bite_basilisk_mm_mm"
        }
      },
      "effects": [],
      "_id": "p0nzdad7jubfbrzv",
      "folder": null,
      "sort": 0,
      "permission": {
        "default": 0
      }
    },
    {
      "name": "Petrifying Gaze",
      "type": "feat",
      "data": {
        "description": {
          "value": "<div  class=\"rd__b  rd__b--3\"><p>If a creature starts its turn within 30 feet of the basilisk and the two of them can see each other, the basilisk can force the creature to make a DC <span class=\"rd__dc\">12</span> Constitution saving throw if the basilisk isn't @condition[incapacitated]. On a failed save, the creature magically begins to turn to stone and is @condition[restrained]. It must repeat the saving throw at the end of its next turn. On a success, the effect ends. On a failure, the creature is @condition[petrified] until freed by the  @spell[greater restoration] spell or other magic.</p><div class=\"rd__spc-inline-post\"></div><p>A creature that isn't surprised can avert its eyes to avoid the saving throw at the start of its turn. If it does so, it can't see the basilisk until the start of its next turn, when it can avert its eyes again. If it looks at the basilisk in the meantime, it must immediately make the save.</p><p>If the basilisk sees its reflection within 30 feet of it in bright light, it mistakes itself for a rival and targets itself with its gaze.</p></div>",
          "chat": "",
          "unidentified": ""
        },
        "source": "MM",
        "activation": {
          "type": "",
          "cost": 0,
          "condition": ""
        },
        "duration": {
          "value": null,
          "units": ""
        },
        "target": {
          "value": null,
          "width": null,
          "units": "",
          "type": ""
        },
        "range": {
          "value": null,
          "long": null,
          "units": ""
        },
        "uses": {
          "value": null,
          "max": "",
          "per": null
        },
        "consume": {
          "type": null,
          "target": null,
          "amount": null
        },
        "ability": null,
        "actionType": "save",
        "attackBonus": 0,
        "chatFlavor": "",
        "critical": {
          "threshold": null,
          "damage": ""
        },
        "damage": {
          "parts": [],
          "versatile": ""
        },
        "formula": "",
        "save": {
          "ability": "con",
          "dc": 12,
          "scaling": "con"
        },
        "requirements": "",
        "recharge": {
          "value": null,
          "charged": false
        }
      },
      "img": "https://assets.forge-vtt.com/bazaar/core/icons/magic/control/hypnosis-mesmerism-eye.webp",
      "flags": {
        "srd5e": {
          "page": "monsterTrait",
          "source": "MM",
          "hash": "petrifying%20gaze_basilisk_mm_mm"
        }
      },
      "effects": [],
      "_id": "qyjeca8tl9i5etqz",
      "folder": null,
      "sort": 0,
      "permission": {
        "default": 0
      }
    }
  ],
  "effects": [],
  "folder": null,
  "sort": 0,
  "permission": {
    "default": 0,
    "UjfixXuqstXNdypa": 3
  },
  "flags": {
    "srd5e": {
      "page": "bestiary.html",
      "source": "MM",
      "hash": "basilisk_mm"
    }
  },
  "_id": "SibFXQk8qWn0fHYC"
}